humilis_batch_job
