Metadata-Version: 1.1
Name: humilis-batch-job
Version: 0.1.9
Summary: Humilis plug-in to deploy a scheduled AWS Batch job
Home-page: https://github.com/humilis/humilis-batch-job
Author: German Gomez-Herrero, FindHotel BV
Author-email: german@findhotel.net
License: MIT
Platform: UNKNOWN
Classifier: Programming Language :: Python :: 3
